package_sampling/__init__.py
package_sampling/sampling/__init__.py
package_sampling/sampling/up_brewer.py
package_sampling/sampling/up_max_entropy.py
package_sampling/sampling/up_max_entropy_pi2.py
package_sampling/sampling/up_poisson.py
package_sampling/sampling/up_systematic.py
package_sampling/sampling/up_systematic_pi2.py
package_sampling/sampling/up_tille.py
package_sampling/sampling/up_tille_pi2.py
package_sampling/sampling/upme_pik2_from_pik_w.py
package_sampling/sampling/upme_pik_from_q.py
package_sampling/sampling/upme_pik_tilde_from_pik.py
package_sampling/sampling/upme_q_from_w.py
package_sampling/sampling/upme_s_from_q.py
package_sampling/utils/__init__.py
package_sampling/utils/as_int.py
package_sampling/utils/inclusion_probabilities.py
package_sampling-1.0.0.dist-info/LICENSE
package_sampling-1.0.0.dist-info/METADATA
package_sampling-1.0.0.dist-info/WHEEL
package_sampling-1.0.0.dist-info/RECORD
