Metadata-Version: 2.3
Name: package-sampling
Version: 1.0.0
Summary: Python implementation of probability-based sampling algorithms inspired by the R package Sampling.
License: MIT
Author: Mohammadreza Razavian
Author-email: smrrazavian@outlook.com
Requires-Python: >=3.8
Classifier: License :: OSI Approved :: MIT License
Classifier: Programming Language :: Python :: 3
Classifier: Programming Language :: Python :: 3.8
Classifier: Programming Language :: Python :: 3.9
Classifier: Programming Language :: Python :: 3.10
Classifier: Programming Language :: Python :: 3.11
Classifier: Programming Language :: Python :: 3.12
Classifier: Programming Language :: Python :: 3.13
Requires-Dist: numpy (>=1.26,<2.0)
Project-URL: Homepage, https://github.com/smrrazavian/package-sampling
Project-URL: Repository, https://github.com/smrrazavian/package-sampling
